{  "broken_arrow_bins":{
      "bin_id_0":{
         "bin":"A1A"
      },
      "bin_id_1":{
         "bin":"A1B"
      },
      "bin_id_2":{
         "bin":"A1C"
      },
      "bin_id_3":{
         "bin":"A1D"
      },
      "bin_id_4":{
         "bin":"A1E"
      },
      "bin_id_5":{
         "bin":"A2A"
      },
      "bin_id_6":{
         "bin":"A2B"
      },
      "bin_id_7":{
         "bin":"A2C"
      },
      "bin_id_8":{
         "bin":"A2D"
      },
      "bin_id_9":{
         "bin":"A2E"
      },
      "bin_id_10":{
         "bin":"A3A"
      },
      "bin_id_11":{
         "bin":"A3B"
      },
      "bin_id_12":{
         "bin":"A3C"
      },
      "bin_id_13":{
         "bin":"A3D"
      },
      "bin_id_14":{
         "bin":"A3E"
      },
      "bin_id_15":{
         "bin":"A4A"
      },
      "bin_id_16":{
         "bin":"A4B"
      },
      "bin_id_17":{
         "bin":"A4C"
      },
      "bin_id_18":{
         "bin":"A4D"
      },
      "bin_id_19":{
         "bin":"A4E"
      },
      "bin_id_20":{
         "bin":"A5A"
      },
      "bin_id_21":{
         "bin":"A5B"
      },
      "bin_id_22":{
         "bin":"A5C"
      },
      "bin_id_23":{
         "bin":"A5D"
      },
      "bin_id_24":{
         "bin":"A5E"
      },
      "bin_id_25":{
         "bin":"A6A"
      },
      "bin_id_26":{
         "bin":"A6B"
      },
      "bin_id_27":{
         "bin":"A6C"
      },
      "bin_id_28":{
         "bin":"SO"
      },
      "bin_id_29":{
         "bin":"SOP"
      }
    },
  "jenks_bins":{
      "bin_id_0":{
         "bin":"A1A"
      },
      "bin_id_1":{
         "bin":"A1B"
      },
      "bin_id_2":{
         "bin":"A1C"
      },
      "bin_id_3":{
         "bin":"A1D"
      },
      "bin_id_4":{
         "bin":"A1E"
      },
      "bin_id_5":{
         "bin":"A2A"
      },
      "bin_id_6":{
         "bin":"A2B"
      },
      "bin_id_7":{
         "bin":"A2C"
      },
      "bin_id_8":{
         "bin":"A2D"
      },
      "bin_id_9":{
         "bin":"A2E"
      },
      "bin_id_10":{
         "bin":"A3A"
      },
      "bin_id_11":{
         "bin":"A3B"
      },
      "bin_id_12":{
         "bin":"A3C"
      },
      "bin_id_13":{
         "bin":"A3D"
      },
      "bin_id_14":{
         "bin":"A3E"
      },
      "bin_id_15":{
         "bin":"A4A"
      },
      "bin_id_16":{
         "bin":"A4B"
      },
      "bin_id_17":{
         "bin":"A4C"
      },
      "bin_id_18":{
         "bin":"A4D"
      },
      "bin_id_19":{
         "bin":"A4E"
      },
      "bin_id_20":{
         "bin":"A5A"
      },
      "bin_id_21":{
         "bin":"A5B"
      },
      "bin_id_22":{
         "bin":"A5C"
      },
      "bin_id_23":{
         "bin":"A5D"
      },
      "bin_id_24":{
         "bin":"A5E"
      },
      "bin_id_25":{
         "bin":"A6A"
      },
      "bin_id_26":{
         "bin":"A6B"
      },
      "bin_id_27":{
         "bin":"A6C"
      },
      "bin_id_28":{
         "bin":"SO"
      },
      "bin_id_29":{
         "bin":"SOP"
      }
    },
  "bixby_bins":{
      "bin_id_0":{
         "bin":"A1A"
      },
      "bin_id_1":{
         "bin":"A1B"
      },
      "bin_id_2":{
         "bin":"A1C"
      },
      "bin_id_3":{
         "bin":"A1D"
      },
      "bin_id_4":{
         "bin":"A1E"
      },
      "bin_id_5":{
         "bin":"A2B"
      },
      "bin_id_6":{
         "bin":"A2C"
      },
      "bin_id_7":{
         "bin":"A2D"
      },
      "bin_id_8":{
         "bin":"A2E"
      },
      "bin_id_9":{
         "bin":"A3E"
      },
      "bin_id_10":{
         "bin":"A4B"
      },
      "bin_id_11":{
         "bin":"A4C"
      },
      "bin_id_12":{
         "bin":"A4D"
      },
      "bin_id_13":{
         "bin":"A4E"
      },
      "bin_id_14":{
         "bin":"A5A"
      },
      "bin_id_15":{
         "bin":"A5B"
      },
      "bin_id_16":{
         "bin":"A5C"
      },
      "bin_id_17":{
         "bin":"A6A"
      },
      "bin_id_18":{
         "bin":"A6C"
      },
      "bin_id_19":{
         "bin":"A6D"
      },
      "bin_id_20":{
         "bin":"A6E"
      },
      "bin_id_21":{
         "bin":"A7A"
      },
      "bin_id_22":{
         "bin":"A7B"
      },
      "bin_id_23":{
         "bin":"A7C"
      }
    },
  "downtown_bins":{
      "bin_id_0":{
         "bin":"A1B"
      },
      "bin_id_1":{
         "bin":"A1C"
      },
      "bin_id_2":{
         "bin":"A1E"
      },
      "bin_id_3":{
         "bin":"A2A"
      },
      "bin_id_4":{
         "bin":"A2B"
      },
      "bin_id_5":{
         "bin":"A2C"
      },
      "bin_id_6":{
         "bin":"A2D"
      },
      "bin_id_7":{
         "bin":"A3B"
      },
      "bin_id_8":{
         "bin":"A3C"
      },
      "bin_id_9":{
         "bin":"A3D"
      },
      "bin_id_10":{
         "bin":"A3E"
      },
      "bin_id_11":{
         "bin":"A4A"
      },
      "bin_id_12":{
         "bin":"A4C"
      },
      "bin_id_13":{
         "bin":"A4D"
      },
      "bin_id_14":{
         "bin":"A4E"
      }
    },
  "fayetteville_bins":{
      "bin_id_0":{
         "bin":"A1A"
      },
      "bin_id_1":{
         "bin":"A1B"
      },
      "bin_id_2":{
         "bin":"A1C"
      },
      "bin_id_3":{
         "bin":"A1E"
      },
      "bin_id_4":{
         "bin":"A1F"
      },
      "bin_id_5":{
         "bin":"A1G"
      },
      "bin_id_6":{
         "bin":"A1H"
      },
      "bin_id_7":{
         "bin":"A1J"
      },
      "bin_id_8":{
         "bin":"A1K"
      },
      "bin_id_9":{
         "bin":"A2A"
      },
      "bin_id_10":{
         "bin":"A2B"
      },
      "bin_id_11":{
         "bin":"A2C"
      },
      "bin_id_12":{
         "bin":"A2D"
      },
      "bin_id_13":{
         "bin":"A2E"
      },
      "bin_id_14":{
         "bin":"A2G"
      },
      "bin_id_15":{
         "bin":"A2J"
      },
      "bin_id_16":{
         "bin":"A2K"
      },
      "bin_id_17":{
         "bin":"A3F"
      },
      "bin_id_18":{
         "bin":"A3G"
      },
      "bin_id_19":{
         "bin":"A3H"
      },
      "bin_id_20":{
         "bin":"A3J"
      },
      "bin_id_21":{
         "bin":"A3K"
      },
      "bin_id_22":{
         "bin":"A4A"
      },
      "bin_id_23":{
         "bin":"A4B"
      },
      "bin_id_24":{
         "bin":"A4C"
      },
      "bin_id_25":{
         "bin":"A4D"
      },
      "bin_id_26":{
         "bin":"A4E"
      },
      "bin_id_27":{
         "bin":"A4F"
      },
      "bin_id_28":{
         "bin":"A4G"
      },
      "bin_id_29":{
         "bin":"A4H"
      },
      "bin_id_30":{
         "bin":"A4K"
      },
      "bin_id_31":{
         "bin":"A5A"
      },
      "bin_id_32":{
         "bin":"A5F"
      },
      "bin_id_33":{
         "bin":"A5H"
      },
      "bin_id_34":{
         "bin":"A5J"
      },
      "bin_id_35":{
         "bin":"A5K"
      },
      "bin_id_36":{
         "bin":"A8A"
      },
      "bin_id_37":{
         "bin":"A8B"
      },
      "bin_id_38":{
         "bin":"A8C"
      },
      "bin_id_39":{
         "bin":"A8D"
      },
      "bin_id_40":{
         "bin":"SOP"
      },
      "bin_id_41":{
         "bin":"NDP"
      },
      "bin_id_42":{
         "bin":"1C"
      }
    },
  "fort_smith_bins":{
      "bin_id_0":{
         "bin":"A1A"
      },
      "bin_id_1":{
         "bin":"A1B"
      },
      "bin_id_2":{
         "bin":"A1C"
      },
      "bin_id_3":{
         "bin":"A1D"
      },
      "bin_id_4":{
         "bin":"A1E"
      },
      "bin_id_5":{
         "bin":"A1F"
      },
      "bin_id_6":{
         "bin":"A1G"
      },
      "bin_id_7":{
         "bin":"A1H"
      },
      "bin_id_8":{
         "bin":"A1J"
      },
      "bin_id_9":{
         "bin":"A1K"
      },
      "bin_id_10":{
         "bin":"A2A"
      },
      "bin_id_11":{
         "bin":"A2C"
      },
      "bin_id_12":{
         "bin":"A2D"
      },
      "bin_id_13":{
         "bin":"A2E"
      },
      "bin_id_14":{
         "bin":"A2F"
      },
      "bin_id_15":{
         "bin":"A2G"
      },
      "bin_id_16":{
         "bin":"A2H"
      },
      "bin_id_17":{
         "bin":"A2J"
      },
      "bin_id_18":{
         "bin":"A2K"
      },
      "bin_id_19":{
         "bin":"A3D"
      },
      "bin_id_20":{
         "bin":"A2E"
      },
      "bin_id_21":{
         "bin":"A3F"
      },
      "bin_id_22":{
         "bin":"A3G"
      },
      "bin_id_23":{
         "bin":"A3H"
      },
      "bin_id_24":{
         "bin":"A3J"
      },
      "bin_id_25":{
         "bin":"A3K"
      },
      "bin_id_26":{
         "bin":"A4A"
      },
      "bin_id_27":{
         "bin":"A4B"
      },
      "bin_id_28":{
         "bin":"A4C"
      },
      "bin_id_29":{
         "bin":"A4D"
      },
      "bin_id_30":{
         "bin":"A4E"
      },
      "bin_id_31":{
         "bin":"A4F"
      },
      "bin_id_32":{
         "bin":"A4G"
      },
      "bin_id_33":{
         "bin":"A4H"
      },
      "bin_id_34":{
         "bin":"A4J"
      },
      "bin_id_35":{
         "bin":"A4K"
      },
      "bin_id_36":{
         "bin":"A5A"
      },
      "bin_id_37":{
         "bin":"A7A"
      },
      "bin_id_38":{
         "bin":"A7B"
      },
      "bin_id_39":{
         "bin":"A7C"
      },
      "bin_id_40":{
         "bin":"A7D"
      },
      "bin_id_41":{
         "bin":"A8A"
      },
      "bin_id_42":{
         "bin":"SOP"
      },
      "bin_id_43":{
         "bin":"NDP"
      },
      "bin_id_44":{
         "bin":"1F"
      }
    },
  "71st_bins":{
      "bin_id_0":{
         "bin":"A1L"
      },
      "bin_id_1":{
         "bin":"A1M"
      },
      "bin_id_2":{
         "bin":"A1N"
      },
      "bin_id_3":{
         "bin":"A1P"
      },
      "bin_id_4":{
         "bin":"A1Q"
      },
      "bin_id_5":{
         "bin":"A1R"
      },
      "bin_id_6":{
         "bin":"A1S"
      },
      "bin_id_7":{
         "bin":"A1T"
      },
      "bin_id_8":{
         "bin":"A1U"
      },
      "bin_id_9":{
         "bin":"A1V"
      },
      "bin_id_10":{
         "bin":"A1W"
      },
      "bin_id_11":{
         "bin":"A1X"
      },
      "bin_id_12":{
         "bin":"A1Y"
      },
      "bin_id_13":{
         "bin":"A1Z"
      },
      "bin_id_14":{
         "bin":"A2G"
      },
      "bin_id_15":{
         "bin":"A2H"
      },
      "bin_id_16":{
         "bin":"A2J"
      },
      "bin_id_17":{
         "bin":"A2K"
      },
      "bin_id_18":{
         "bin":"A2L"
      },
      "bin_id_19":{
         "bin":"A2M"
      },
      "bin_id_20":{
         "bin":"A2N"
      },
      "bin_id_21":{
         "bin":"A2P"
      },
      "bin_id_22":{
         "bin":"A2Q"
      },
      "bin_id_23":{
         "bin":"A2R"
      },
      "bin_id_24":{
         "bin":"A2S"
      },
      "bin_id_25":{
         "bin":"A2T"
      },
      "bin_id_26":{
         "bin":"A2U"
      },
      "bin_id_27":{
         "bin":"A2V"
      },
      "bin_id_28":{
         "bin":"A2W"
      },
      "bin_id_29":{
         "bin":"A2X"
      },
      "bin_id_30":{
         "bin":"A2Y"
      },
      "bin_id_31":{
         "bin":"A2Z"
      },
      "bin_id_32":{
         "bin":"A3A"
      },
      "bin_id_33":{
         "bin":"A3B"
      },
      "bin_id_34":{
         "bin":"A3C"
      },
      "bin_id_35":{
         "bin":"A3D"
      },
      "bin_id_36":{
         "bin":"A3E"
      },
      "bin_id_37":{
         "bin":"A3F"
      },
      "bin_id_38":{
         "bin":"A3G"
      },
      "bin_id_39":{
         "bin":"A3H"
      },
      "bin_id_40":{
         "bin":"A3J"
      },
      "bin_id_41":{
         "bin":"A3K"
      },
      "bin_id_42":{
         "bin":"A3L"
      },
      "bin_id_43":{
         "bin":"A3M"
      },
      "bin_id_44":{
         "bin":"A3N"
      },
      "bin_id_45":{
         "bin":"A3P"
      },
      "bin_id_46":{
         "bin":"A3Q"
      },
      "bin_id_47":{
         "bin":"A3R"
      },
      "bin_id_48":{
         "bin":"A3S"
      },
      "bin_id_49":{
         "bin":"A3T"
      },
      "bin_id_50":{
         "bin":"A3U"
      },
      "bin_id_51":{
         "bin":"A3V"
      },
      "bin_id_52":{
         "bin":"A3W"
      },
      "bin_id_53":{
         "bin":"A3X"
      },
      "bin_id_54":{
         "bin":"A3Y"
      },
      "bin_id_55":{
         "bin":"A3Z"
      },
      "bin_id_56":{
         "bin":"A4A"
      },
      "bin_id_57":{
         "bin":"A4B"
      },
      "bin_id_58":{
         "bin":"A4C"
      },
      "bin_id_59":{
         "bin":"A4D"
      },
      "bin_id_60":{
         "bin":"A4E"
      },
      "bin_id_61":{
         "bin":"A4F"
      },
      "bin_id_62":{
         "bin":"A4G"
      },
      "bin_id_63":{
         "bin":"A4H"
      },
      "bin_id_64":{
         "bin":"A4J"
      },
      "bin_id_65":{
         "bin":"A4K"
      },
      "bin_id_66":{
         "bin":"A4L"
      },
      "bin_id_67":{
         "bin":"A4M"
      },
      "bin_id_68":{
         "bin":"A4N"
      },
      "bin_id_69":{
         "bin":"A4P"
      },
      "bin_id_70":{
         "bin":"A4Q"
      },
      "bin_id_71":{
         "bin":"A4R"
      },
      "bin_id_72":{
         "bin":"A4S"
      },
      "bin_id_73":{
         "bin":"A4T"
      },
      "bin_id_74":{
         "bin":"A4U"
      },
      "bin_id_75":{
         "bin":"A4V"
      },
      "bin_id_76":{
         "bin":"A4W"
      },
      "bin_id_77":{
         "bin":"A4X"
      },
      "bin_id_78":{
         "bin":"A4Y"
      },
      "bin_id_79":{
         "bin":"A4Z"
      },
      "bin_id_80":{
         "bin":"A5A"
      },
      "bin_id_81":{
         "bin":"A5B"
      },
      "bin_id_82":{
         "bin":"A5C"
      },
      "bin_id_83":{
         "bin":"A5G"
      },
      "bin_id_84":{
         "bin":"A5H"
      },
      "bin_id_85":{
         "bin":"A5J"
      },
      "bin_id_86":{
         "bin":"A5K"
      },
      "bin_id_87":{
         "bin":"A5L"
      },
      "bin_id_88":{
         "bin":"A5M"
      },
      "bin_id_89":{
         "bin":"A5N"
      }
    },
  "owasso_bins":{
      "bin_id_0":{
         "bin":"A1B"
      },
      "bin_id_1":{
         "bin":"A1H"
      },
      "bin_id_2":{
         "bin":"A2A"
      },
      "bin_id_3":{
         "bin":"A2B"
      },
      "bin_id_4":{
         "bin":"A2C"
      },
      "bin_id_5":{
         "bin":"A2D"
      },
      "bin_id_6":{
         "bin":"A2E"
      },
      "bin_id_7":{
         "bin":"A2G"
      },
      "bin_id_8":{
         "bin":"A2H"
      },
      "bin_id_9":{
         "bin":"A2J"
      },
      "bin_id_10":{
         "bin":"A2K"
      },
      "bin_id_11":{
         "bin":"A2L"
      },
      "bin_id_12":{
         "bin":"A3A"
      },
      "bin_id_13":{
         "bin":"A3B"
      },
      "bin_id_14":{
         "bin":"A3C"
      },
      "bin_id_15":{
         "bin":"A3D"
      },
      "bin_id_16":{
         "bin":"A3E"
      },
      "bin_id_17":{
         "bin":"A3G"
      },
      "bin_id_18":{
         "bin":"A3J"
      },
      "bin_id_19":{
         "bin":"A3K"
      },
      "bin_id_20":{
         "bin":"A3L"
      },
      "bin_id_21":{
         "bin":"A4A"
      },
      "bin_id_22":{
         "bin":"A4B"
      },
      "bin_id_23":{
         "bin":"A4C"
      },
      "bin_id_24":{
         "bin":"A4D"
      },
      "bin_id_25":{
         "bin":"A4E"
      },
      "bin_id_26":{
         "bin":"A4F"
      },
      "bin_id_27":{
         "bin":"A4G"
      },
      "bin_id_28":{
         "bin":"A4H"
      },
      "bin_id_29":{
         "bin":"A4J"
      },
      "bin_id_30":{
         "bin":"A4K"
      },
      "bin_id_31":{
         "bin":"A4L"
      },
      "bin_id_32":{
         "bin":"A5A"
      },
      "bin_id_33":{
         "bin":"A5B"
      },
      "bin_id_34":{
         "bin":"A5C"
      },
      "bin_id_35":{
         "bin":"A5D"
      },
      "bin_id_36":{
         "bin":"A5K"
      },
      "bin_id_37":{
         "bin":"A6A"
      },
      "bin_id_38":{
         "bin":"A6B"
      },
      "bin_id_39":{
         "bin":"A6H"
      },
      "bin_id_40":{
         "bin":"A7F"
      },
      "bin_id_41":{
         "bin":"A8G"
      },
      "bin_id_42":{
         "bin":"A9A"
      },
      "bin_id_43":{
         "bin":"A9B"
      },
      "bin_id_44":{
         "bin":"A9C"
      },
      "bin_id_45":{
         "bin":"A9D"
      },
      "bin_id_46":{
         "bin":"A9E"
      },
      "bin_id_47":{
         "bin":"DSK"
      }
    },
  "tahlequah_bins":{
      "bin_id_0":{
         "bin":"A1A"
      },
      "bin_id_1":{
         "bin":"A1B"
      },
      "bin_id_2":{
         "bin":"A1C"
      },
      "bin_id_3":{
         "bin":"A1D"
      },
      "bin_id_4":{
         "bin":"A1E"
      },
      "bin_id_5":{
         "bin":"A2A"
      },
      "bin_id_6":{
         "bin":"A2B"
      },
      "bin_id_7":{
         "bin":"A2C"
      },
      "bin_id_8":{
         "bin":"A2D"
      },
      "bin_id_9":{
         "bin":"A2E"
      },
      "bin_id_10":{
         "bin":"A3A"
      },
      "bin_id_11":{
         "bin":"A3B"
      },
      "bin_id_12":{
         "bin":"A3C"
      },
      "bin_id_13":{
         "bin":"A3D"
      },
      "bin_id_14":{
         "bin":"A3E"
      },
      "bin_id_15":{
         "bin":"A4A"
      },
      "bin_id_16":{
         "bin":"A4B"
      },
      "bin_id_17":{
         "bin":"A4C"
      },
      "bin_id_18":{
         "bin":"A4D"
      },
      "bin_id_19":{
         "bin":"A4E"
      },
      "bin_id_20":{
         "bin":"A5A"
      },
      "bin_id_21":{
         "bin":"A5B"
      },
      "bin_id_22":{
         "bin":"A5C"
      },
      "bin_id_23":{
         "bin":"A5D"
      },
      "bin_id_24":{
         "bin":"A5E"
      },
      "bin_id_25":{
         "bin":"A6A"
      },
      "bin_id_26":{
         "bin":"A6B"
      },
      "bin_id_27":{
         "bin":"A6C"
      }
    },
  "21st_bins":{
      "bin_id_0":{
         "bin":"A1A"
      },
      "bin_id_1":{
         "bin":"A1B"
      },
      "bin_id_2":{
         "bin":"A1C"
      },
      "bin_id_3":{
         "bin":"A2A"
      },
      "bin_id_4":{
         "bin":"A2B"
      },
      "bin_id_5":{
         "bin":"A2C"
      },
      "bin_id_6":{
         "bin":"A3A"
      },
      "bin_id_7":{
         "bin":"A3B"
      },
      "bin_id_8":{
         "bin":"A3C"
      },
      "bin_id_9":{
         "bin":"A3D"
      },
      "bin_id_10":{
         "bin":"A4A"
      },
      "bin_id_11":{
         "bin":"A4C"
      },
      "bin_id_12":{
         "bin":"A4D"
      },
      "bin_id_13":{
         "bin":"A4E"
      },
      "bin_id_14":{
         "bin":"A5A"
      },
      "bin_id_15":{
         "bin":"9A9"
      },
      "bin_id_16":{
         "bin":"SP"
      }
   }
}

